AUTHORS
LICENSE
MANIFEST.in
README.rst
setup.py
bootstrap3_wysihtml5x/__init__.py
bootstrap3_wysihtml5x/admin.py
bootstrap3_wysihtml5x/apps.py
bootstrap3_wysihtml5x/fields.py
bootstrap3_wysihtml5x/models.py
bootstrap3_wysihtml5x/utils.py
bootstrap3_wysihtml5x/widgets.py
bootstrap3_wysihtml5x/conf/__init__.py
bootstrap3_wysihtml5x/conf/defaults.py
bootstrap3_wysihtml5x/static/bootstrap3_wysihtml5x/css/stylesheet.css
bootstrap3_wysihtml5x/static/bootstrap3_wysihtml5x/css/toolbar.css
bootstrap3_wysihtml5x/static/bootstrap3_wysihtml5x/img/toolbar.png
bootstrap3_wysihtml5x/static/bootstrap3_wysihtml5x/js/wysihtml5x-toolbar.min.js
bootstrap3_wysihtml5x/static/bootstrap3_wysihtml5x/js/wysihtml5x.min.js
bootstrap3_wysihtml5x/tests/__init__.py
bootstrap3_wysihtml5x/tests/fields.py
bootstrap3_wysihtml5x/tests/models.py
bootstrap3_wysihtml5x/tests/settings.py
bootstrap3_wysihtml5x/tests/widgets.py
django_bootstrap3_wysihtml5x.egg-info/PKG-INFO
django_bootstrap3_wysihtml5x.egg-info/SOURCES.txt
django_bootstrap3_wysihtml5x.egg-info/dependency_links.txt
django_bootstrap3_wysihtml5x.egg-info/top_level.txt