Metadata-Version: 1.1
Name: django-bootstrap3-wysihtml5x
Version: 1.0
Summary: Simple Django app that provides a Wysihtml5x rich-text editor widget.
Home-page: http://pypi.python.org/pypi/django-bootstrap3-wysihtml5x/
Author: Cédric Foellmi
Author-email: cedric@onekilopars.ec
License: MIT
Platform: UNKNOWN
Classifier: Development Status :: 4 - Beta
Classifier: Environment :: Web Environment
Classifier: Intended Audience :: Developers
Classifier: License :: OSI Approved :: MIT License
Classifier: Operating System :: OS Independent
Classifier: Programming Language :: Python
Classifier: Programming Language :: Python :: 3
Classifier: Framework :: Django
